sortfolder.py
sortfolder-1.0.0.dist-info/LICENSE
sortfolder-1.0.0.dist-info/METADATA
sortfolder-1.0.0.dist-info/WHEEL
sortfolder-1.0.0.dist-info/entry_points.txt
sortfolder-1.0.0.dist-info/top_level.txt
sortfolder-1.0.0.dist-info/RECORD
